offyt.py
setup.py
offyt.egg-info/PKG-INFO
offyt.egg-info/SOURCES.txt
offyt.egg-info/dependency_links.txt
offyt.egg-info/requires.txt
offyt.egg-info/top_level.txt