Metadata-Version: 1.0
Name: offyt
Version: 0.1.3
Summary: Offline YouTube Playlist Synchronization
Home-page: https://github.com/koenbollen/offyt
Author: Koen Bollen
Author-email: meneer@koenbollen.nl
License: ISC
Keywords: youtube offline playlist synchronization download
Platform: UNKNOWN
